tero/__init__.py
tero/crypt.py
tero/dauthcmd.py
tero/dcopylogs.py
tero/dissues.py
tero/dlogwatch.py
tero/dparselog.py
tero/dregress.py
tero/driver.py
tero/drundocker.py
tero/dstamp.py
tero/duploades.py
tero/vmware.py
tero/clouds/__init__.py
tero/clouds/awscloud.py
tero/clouds/monitor.py
tero/clouds/templates/app-cloud-init-script.j2
tero/clouds/templates/dbs-cloud-init-script.j2
tero/clouds/templates/mail-cloud-init-script.j2
tero/clouds/templates/sally-cloud-init-script.j2
tero/clouds/templates/web-cloud-init-script.j2
tero/setup/__init__.py
tero/setup/bash.py
tero/setup/cron.py
tero/setup/docker.py
tero/setup/dovecot.py
tero/setup/fail2ban.py
tero/setup/integrity.py
tero/setup/iptables.py
tero/setup/jenkins.py
tero/setup/local.py
tero/setup/logrotate.py
tero/setup/monit.py
tero/setup/nginx.py
tero/setup/openssh.py
tero/setup/postfix.py
tero/setup/postgres.py
tero/setup/sldap.py
tero/setup/ssmtp.py
tero/setup/sssd.py
tero/setup/syslog.py
tero-1.0.0.dist-info/METADATA
tero-1.0.0.dist-info/WHEEL
tero-1.0.0.dist-info/top_level.txt
tero-1.0.0.dist-info/RECORD
