Metadata-Version: 2.1
Name: tero
Version: 1.0.0
Summary: Configures development machines to cloud resources
Author-email: The DjaoDjin Team <help@djaodjin.com>
Maintainer-email: The DjaoDjin Team <help@djaodjin.com>
License: BSD-2-Clause
Project-URL: repository, https://github.com/djaodjin/drop
Project-URL: documentation, https://drop.readthedocs.io/
Project-URL: changelog, https://github.com/djaodjin/drop/changelog
Keywords: scripts,cloud,configure,paas,saas
Classifier: Environment :: Web Environment
Classifier: Programming Language :: Python
Classifier: License :: OSI Approved :: BSD License
Requires-Python: >=3.7
Requires-Dist: awscli >=1.31.5
Requires-Dist: boto3 >=1.33.5
Requires-Dist: paramiko >=2.12.0
Requires-Dist: pyasn1-modules >=0.2.5
Requires-Dist: pyOpenSSL >=22.1.0
Requires-Dist: pytz >=2023.3
Requires-Dist: requests >=2.31.0
Requires-Dist: six >=1.16.0
Requires-Dist: sqlparse >=0.4.2
